freedvtnc2/__init__.py
freedvtnc2/__main__.py
freedvtnc2/audio.py
freedvtnc2/freedv_build.py
freedvtnc2/modem.py
freedvtnc2/rigctl.py
freedvtnc2/shell.py
freedvtnc2/test_audio.py
freedvtnc2/test_modem.py
freedvtnc2/tnc.py
_freedv_cffi.cpython-311-darwin.so
freedvtnc2-0.0.1.dist-info/METADATA
freedvtnc2-0.0.1.dist-info/WHEEL
freedvtnc2-0.0.1.dist-info/entry_points.txt
freedvtnc2-0.0.1.dist-info/RECORD
