Metadata-Version: 2.1
Name: freedvtnc2
Version: 0.0.1
Summary: 
Author: xssfox
Author-email: xss@sprocketfox.io
Requires-Python: >=3.11,<4.0
Classifier: Programming Language :: Python :: 3
Classifier: Programming Language :: Python :: 3.11
Classifier: Programming Language :: Python :: 3.12
Requires-Dist: cffi (>=1.16.0,<2.0.0)
Requires-Dist: configargparse (>=1.7,<2.0)
Requires-Dist: kissfix (>=7.0.11,<8.0.0)
Requires-Dist: prompt-toolkit (>=3.0.43,<4.0.0)
Requires-Dist: pyaudio (>=0.2.14,<0.3.0)
Requires-Dist: pydub (>=0.25.1,<0.26.0)
Requires-Dist: setuptools (>=69.0.3,<70.0.0)
Requires-Dist: tabulate (>=0.9.0,<0.10.0)
